wrensh/__init__.py
wrensh/text.py
wrensh-0.0.1.dist-info/LICENSE
wrensh-0.0.1.dist-info/METADATA
wrensh-0.0.1.dist-info/WHEEL
wrensh-0.0.1.dist-info/top_level.txt
wrensh-0.0.1.dist-info/RECORD
