Metadata-Version: 2.1
Name: wrensh
Version: 0.0.1
Summary: Library for building UNIX-style pipelines in Python
Author-email: Sean Mackrory <mackrorysd@apache.org>
Project-URL: Homepage, https://github.com/mackrorysd/wrensh
Project-URL: Bug Tracker, https://github.com/mackrorysd/wrensh/issues
Classifier: Programming Language :: Python :: 3
Classifier: License :: OSI Approved :: BSD License
Classifier: Operating System :: OS Independent
Requires-Python: >=3.7
License-File: LICENSE
